LICENSE
MANIFEST.in
README.md
pyproject.toml
requirements.txt
setup.py
camelsml/__init__.py
camelsml/datasets.py
camelsml/datautils.py
camelsml/ealstm.py
camelsml/lstm.py
camelsml/main.py
camelsml/metrics.py
camelsml/nseloss.py
camelsml/permutation.py
camelsml/split_basins.py
camelsml/utils.py
camelsml/version.py
camelsml.egg-info/PKG-INFO
camelsml.egg-info/SOURCES.txt
camelsml.egg-info/dependency_links.txt
camelsml.egg-info/requires.txt
camelsml.egg-info/top_level.txt
camelsml/tests/__init__.py
camelsml/tests/test_dataset_multi.txt
camelsml/tests/test_dataset_none.txt
camelsml/tests/test_dataset_single.txt
camelsml/tests/test_main.py
camelsml/tests/test_timeseries_selection_gb.txt
camelsml/tests/test_timeseries_selection_us.txt