Metadata-Version: 2.1
Name: camelsml
Version: 2.0.1
Summary: Machine learning for CAMELS_GB (support for more in the future maybe)
Home-page: https://github.com/epigramai/videostream
Author: Frederik Kratzert (original code), Bernhard Nornes Lotsberg (forked code)
Author-email: bernhardnorneslotsberg@gmail.com
License:                                  Apache License
Platform: UNKNOWN
License-File: LICENSE
